[
  {"team":"الاهلي","played":8,"win":6,"draw":1,"lose":1,"goalsDiff":13,"points":19},
  {"team":"Zamalek SC","played":9,"win":6,"draw":2,"lose":1,"goalsDiff":11,"points":20},
  {"team":"Pyramids FC","played":8,"win":4,"draw":2,"lose":2,"goalsDiff":5,"points":14},
  {"team":"AL Masry","played":8,"win":3,"draw":3,"lose":2,"goalsDiff":1,"points":12},
  {"team":"National Bank of Egypt","played":8,"win":2,"draw":3,"lose":3,"goalsDiff":1,"points":9},
  {"team":"Ceramica Cleopatra","played":8,"win":4,"draw":1,"lose":3,"goalsDiff":3,"points":13},
  {"team":"Pharco","played":8,"win":2,"draw":3,"lose":3,"goalsDiff":-8,"points":9},
  {"team":"Petrojet","played":8,"win":1,"draw":2,"lose":5,"goalsDiff":-10,"points":5},
  {"team":"Haras El Hodood","played":8,"win":0,"draw":2,"lose":6,"goalsDiff":-13,"points":2}
]
